pyncat/__init__.py
pyncat-0.0.2.dist-info/LICENSE
pyncat-0.0.2.dist-info/METADATA
pyncat-0.0.2.dist-info/WHEEL
pyncat-0.0.2.dist-info/entry_points.txt
pyncat-0.0.2.dist-info/top_level.txt
pyncat-0.0.2.dist-info/RECORD
