Metadata-Version: 2.1
Name: pyncat
Version: 0.0.2
Summary: A simple, stateful code execution server for Python.
Home-page: https://github.com/marksparkza/pyncat
Author: Mark Jacobson
Author-email: mark@saeon.ac.za
License: MIT
Platform: UNKNOWN
Classifier: Intended Audience :: Developers
Classifier: License :: OSI Approved :: MIT License
Classifier: Operating System :: OS Independent
Classifier: Programming Language :: Python :: 3
Classifier: Topic :: Utilities
Requires-Python: ~=3.7
License-File: LICENSE
